{
  "timestamp": "2025-06-18T07:06:12.578176",
  "cache_timestamp": 1750230372.578182,
  "platform_sentiments": {
    "reddit": {
      "platform": "reddit_scraper",
      "timestamp": "2025-06-18T07:06:12.575188",
      "overall_sentiment": "NEUTRAL",
      "sentiment_score": 50,
      "confidence": 0,
      "total_items": 0,
      "bullish_items": 0,
      "bearish_items": 0,
      "neutral_items": 0,
      "top_keywords": [],
      "analysis_method": "unavailable"
    },
    "twitter": {
      "platform": "twitter_scraper",
      "timestamp": "2025-06-18T07:06:12.575546",
      "overall_sentiment": "NEUTRAL",
      "sentiment_score": 50,
      "confidence": 0,
      "total_items": 0,
      "bullish_items": 0,
      "bearish_items": 0,
      "neutral_items": 0,
      "top_keywords": [],
      "analysis_method": "unavailable"
    }
  }
}